Workbook

Sheet Visão
A1: Assessor KM — Plano do projeto
A2: Data: 10/10/2026 · Responsável: Kauê München
A4: Produto | B4: Assessor de gestão por IA em mensageria (Telegram no piloto, WhatsApp na v2) para donos de pequenas e médias empresas, vendido como extensão da mentoria KM e da comunidade Masi.
A5: Para quem | B5: Empresário que gere equipe (5–100 pessoas), vive no WhatsApp, não usa ferramenta de gestão e perde rotina, prazo e cobrança de equipe.
A6: Tese a validar | B6: 10 empresários pagam R$ 97/mês por um assessor que mantém a rotina de gestão deles funcionando pelo WhatsApp.
A7: Por que não competir de frente | B7: Meu Assessor: 250 mil usuários, R$ 29,90/mês, embaixadores famosos. Ganhar no nicho custa só produto + distribuição que Kauê já tem.
A8: Regra de produto | B8: Toda ação com efeito externo volta para o dono confirmar. Toda ação registrada gera recibo na conversa.
A9: Fora do escopo | B9: Gastos pessoais, cartão da família, pesquisa de preço (isso é o Meu Assessor).
A10: Decisão de canal (11/10) | B10: Fases 0 e 1 no Telegram (piloto, gratuito, reaproveita bot atual). Orquestrador com adaptador de canal; Fase 2 migra para WhatsApp Cloud API. Cobrança da equipe pelo WhatsApp só após a migração. Se >50% dos entrevistados recusarem Telegram, ir direto para Evolution API.
A13: Meu Assessor vs Assessor KM
A14: Meu Assessor | B14: Assessor KM
A15: Organiza a vida pessoal | B15: Organiza a gestão da empresa (metas, rotina, delegação, cobrança de equipe)
A16: Assessores genéricos | B16: Assessor treinado no método de gestão KM/Masi
A17: Cobra clientes | B17: Cobra a equipe por entregas e prazos
A18: Ata de reunião | B18: Ata + tarefas distribuídas + acompanhamento até fechar
A19: R$ 29,90/mês, aquisição paga | B19: R$ 97–197/mês, venda direta para quem já confia em Kauê
A22: Legenda: células amarelas são para você preencher/atualizar (status, datas, decisões).
A23: Abas: Escopo · Módulos · Funções · Ligações · Fases · Tarefas · Necessidades · Custos · Cronograma · Riscos · Decisões

Sheet Escopo
A1: Escopo por versão
A3: Módulo | B3: O que faz | C3: Versão
A4: Rotina (resumo diário) | B4: Manda às 7h: compromissos, tarefas vencendo, cobranças pendentes da equipe | C4: MVP
A5: Agenda | B5: Agenda por áudio/texto no Google Agenda, lembrete antes, link do Meet | C5: MVP
A6: Tarefas e delegação | B6: Cria tarefa, atribui a pessoa da equipe, avisa o dono quando fechar ou atrasar (cobrança direta ao colaborador pelo WhatsApp: v2) | C6: MVP
A7: Ata de reunião | B7: Recebe áudio/gravação, transcreve, gera ata com decisões e ações, cria as tarefas | C7: MVP
A8: Metas semanais | B8: Dono define 3 metas; assessor cobra na sexta e consolida | C8: MVP
A9: Painel web | B9: Tarefas, equipe, metas, histórico em tela grande | C9: v2
A10: Conta compartilhada | B10: Sócios e gestores no mesmo número, cada um com seu WhatsApp, permissões por papel | C10: v2
A11: Documentos | B11: Guarda arquivos por pasta, busca por descrição, avisa vencimento | C11: v2
A12: Cobrança de clientes | B12: Link de pagamento (Asaas), lembrete recorrente, aviso quando cair | C12: v3
A13: Financeiro | B13: Open Finance (Pluggy), gastos por categoria, fluxo de caixa | C13: v3
A14: Nota fiscal | B14: Emissão de NFS-e (Focus NFe) | C14: v3
A15: Integração AgilFac | B15: OPs do dia, produtividade da semana, alerta de atraso | C15: v3

Sheet Módulos
A1: Assessores — módulos, chave liga/desliga e combinações
A2: Diretor é fixo. Mude SIM/NÃO na coluna 'Ligado' para simular a configuração; o painel abaixo e a aba Ligações recalculam.
A4: Módulo | B4: Nome | C4: Funções | D4: Fase | E4: Ligado | F4: Dados próprios | G4: Integrações | H4: Rotinas automáticas
A5: Diretor | B5: Central de gestão (sempre ativo) | C5: Atende a conversa, roteia, consolida, análise gerencial/consultiva, ideias e processos, governança, memória | D5: MVP | E5: SIM | F5: Perfil, metas, ideias, log de decisões, config de módulos/usuários | G5: — | H5: 7h resumo · 20h fechamento · sex 17h semana · dia 26 mês · alerta de anomalia
A6: Secretária | B6: Secretária executiva | C6: Agenda, reuniões/atas, lembretes, e-mail, mensagens, retornos, link de agendamento | D6: MVP (e-mail e link público v2) | E6: SIM | F6: Compromissos, lembretes, atas, retornos, contatos, modelos | G6: Google Calendar, Meet, Gmail | H6: 7h agenda · lembretes · 18h retornos · dom 19h semana
A7: Produção | B7: Gestor de produção — AgilFac | C7: Consulta e movimenta OPs, produtividade (mês 26–25, 528 min/dia, meta 60%), alertas, cobrança de equipe, fechamento dia 26 | D7: v3 (v2 se nicho = confecção) | E7: NÃO | F7: Cache apenas; fonte = banco AgilFac por empresa | G7: API AgilFac (endpoints no Agil.v2, token por empresa) | H7: 7h OPs e atrasos · 12h/17h lançamentos · sex produtividade · dia 26 fechamento
A8: Documentos | B8: Documentos e cadastros | C8: Arquivo, busca por descrição, contratos (vigência/multa), cadastros, validades, dossiê | D8: v2 | E8: NÃO | F8: Índice de arquivos, metadados, cadastros, validades | G8: Cloudflare R2, OCR/IA, Google Drive opcional | H8: Validades no resumo 7h · revisão mensal de cadastros
A9: Financeiro | B9: Gestor financeiro PJ e PF | C9: Carteiras por CNPJ + PF; registro por texto/áudio/foto/extrato; a pagar/receber; conciliação; recorrências; DRE e fluxo; cobrança; NFS-e; análise; dossiê contador | D9: v2 manual · v3 Open Finance/cobrança/nota | E9: NÃO | F9: Carteiras, contas, lançamentos, categorias, regras, metas | G9: Pluggy (leitura), Asaas, Focus NFe, OFX/CSV | H9: 7h vencimentos · alerta fora do padrão · seg caixa · dia 1 DRE · dia 5 contador
A11: Configuração atual
A12: Módulos ligados | B12: =COUNTIF(E5:E9,"SIM") -> 2
A13: O bot é | B13: =IF(B12=1,"Assistente pessoal (só Diretor)",IF(AND(E6="SIM",E7="NÃO",E8="NÃO",E9="NÃO"),"Assistente executivo",IF(AND(E7="SIM",E8="NÃO",E9="NÃO"),"Assessor de produção do AgilFac",IF(AND(E9="SIM",E8="SIM",E6="NÃO",E7="NÃO"),"Controller",IF(B12=5,"Escritório completo","Combinação personalizada"))))) -> Assistente executivo
A14: Ligações ativas | B14: =Ligações!B17 -> 2
A15: Pacote mais próximo | B15: =IF(B12=5,"Escritório completo",IF(AND(E9="SIM",E8="SIM"),"Controller",IF(E7="SIM","Produção",IF(E6="SIM","Executivo","Assistente")))) -> Executivo
A17: Pacotes comerciais
A18: Pacote | B18: Módulos | C18: Para quem | D18: Fase | E18: Preço sugerido (R$/mês)
A19: Assistente | B19: Diretor | C19: mentorado, profissional liberal | D19: MVP | E19: 67
A20: Executivo | B20: Diretor + Secretária | C20: gestor, consultor, vendedor | D20: MVP | E20: 97
A21: Produção | B21: Diretor + Secretária + Produção | C21: cliente AgilFac (confecção) | D21: v2/v3 | E21: 197
A22: Controller | B22: Diretor + Financeiro + Documentos | C22: empresário com várias empresas e PF misturada | D22: v2 | E22: 197
A23: Escritório completo | B23: todos | C23: sócio-gestor, holding como o Grupo K8 | D23: v3 | E23: 297
A25: Preços são proposta inicial para decisão; amarelo = editável. Ordem de construção: Diretor → Secretária → Financeiro manual → Documentos → Produção/AgilFac → integrações financeiras.

Sheet Funções
A1: Funções por módulo
A2: Status e prioridade são editáveis. Filtre por módulo.
A4: Módulo | B4: Função | C4: O que faz | D4: Fase | E4: Prioridade | F4: Status
A5: Diretor | B5: Roteamento | C5: Classifica texto/áudio/foto e aciona o assessor certo; pedido ambíguo pergunta uma vez | D5: MVP | F5: Não iniciada
A6: Diretor | B6: Consolidação | C6: Resumo 7h e fechamento 20h juntando o que cada módulo ligado tem para o dia | D6: MVP | F6: Não iniciada
A7: Diretor | B7: Análise gerencial | C7: Resumo semanal (sexta) e mensal (dia 26): o que andou, travou, fugiu do padrão | D7: MVP | F7: Não iniciada
A8: Diretor | B8: Consultoria | C8: Responde 'o que você faria?' com base no método KM: prioriza, próximo passo, risco | D8: MVP | F8: Não iniciada
A9: Diretor | B9: Ideias e processos | C9: Ideia por áudio → problema → proposta → passos → responsável; guarda e cobra evolução | D9: MVP | F9: Não iniciada
A10: Diretor | B10: Governança | C10: Liga/desliga módulos, usuários e permissões, confirmação antes de ação externa | D10: MVP | F10: Não iniciada
A11: Diretor | B11: Memória | C11: Contexto do dono: empresas, pessoas-chave, metas, preferências | D11: MVP | F11: Não iniciada
A12: Secretária | B12: Agenda | C12: Cria/move/cancela no Google Agenda por áudio ou texto; deslocamento; avisa antes | D12: MVP | F12: Não iniciada
A13: Secretária | B13: Reuniões | C13: Link do Meet, convites, lembrete 1h antes, ata com decisões e ações | D13: MVP | F13: Não iniciada
A14: Secretária | B14: Lembretes | C14: Pontuais e recorrentes; lembra terceiros quando autorizado | D14: MVP | F14: Não iniciada
A15: Secretária | B15: E-mail | C15: Lê Gmail, resume, rascunha respostas para aprovação, arquiva e etiqueta | D15: v2 | F15: Não iniciada
A16: Secretária | B16: Mensagens | C16: Rascunha WhatsApp/Telegram no tom do dono; envia só após OK | D16: MVP | F16: Não iniciada
... A39: Financeiro | B39: Contador | C39: Dossiê mensal por CNPJ: lançamentos, notas, comprovantes | D39: v2 | F39: Não iniciada
A41: Resumo por módulo
A42: Módulo | B42: Funções | C42: Concluídas | D42: % concluído
A43: Diretor | B43: =COUNTIF($A$5:$A$39,A43) -> 7 | C43: =COUNTIFS($A$5:$A$39,A43,$F$5:$F$39,"Concluída") -> 0 | D43: =IF(B43=0,0,C43/B43) -> 0
A44: Secretária | B44: =COUNTIF($A$5:$A$39,A44) -> 7 | C44: =COUNTIFS($A$5:$A$39,A44,$F$5:$F$39,"Concluída") -> 0 | D44: =IF(B44=0,0,C44/B44) -> 0
A45: Produção | B45: =COUNTIF($A$5:$A$39,A45) -> 6 | C45: =COUNTIFS($A$5:$A$39,A45,$F$5:$F$39,"Concluída") -> 0 | D45: =IF(B45=0,0,C45/B45) -> 0
A46: Documentos | B46: =COUNTIF($A$5:$A$39,A46) -> 6 | C46: =COUNTIFS($A$5:$A$39,A46,$F$5:$F$39,"Concluída") -> 0 | D46: =IF(B46=0,0,C46/B46) -> 0
A47: Financeiro | B47: =COUNTIF($A$5:$A$39,A47) -> 9 | C47: =COUNTIFS($A$5:$A$39,A47,$F$5:$F$39,"Concluída") -> 0 | D47: =IF(B47=0,0,C47/B47) -> 0

Sheet Ligações
A1: Ligações entre assessores
A2: Uma ligação só existe quando os dois módulos estão ligados (aba Módulos). A coluna 'Ativa' recalcula.
A4: De | B4: Para | C4: O que passa | D4: Exemplo na conversa | E4: Ativa
A5: Secretária | B5: Financeiro | C5: Compromisso com valor vira conta a pagar/receber | D5: 'Reunião com o Carlos quinta, ele paga os 5 mil' → agenda + conta a receber | E5: =IF(AND(INDEX(Módulos!$E$5:$E$9,MATCH("Secretária",Módulos!$A$5:$A$9,0))="SIM",INDEX(Módulos!$E$5:$E$9,MATCH("Financeiro",Módulos!$A$5:$A$9,0))="SIM"),"SIM","NÃO") -> NÃO
A6: Financeiro | B6: Secretária | C6: Vencimento vira lembrete na agenda | D6: boleto do IPVA aparece no dia do dono | E6: =IF(AND(INDEX(Módulos!$E$5:$E$9,MATCH("Financeiro",Módulos!$A$5:$A$9,0))="SIM",INDEX(Módulos!$E$5:$E$9,MATCH("Secretária",Módulos!$A$5:$A$9,0))="SIM"),"SIM","NÃO") -> NÃO
A7: Produção | B7: Financeiro | C7: OP finalizada/embarcada vira faturamento previsto; folha e prêmio viram custo | D7: 'Fechou o mês: R$ 48 mil a faturar, prêmio R$ 3,2 mil' | E7: =IF(AND(INDEX(Módulos!$E$5:$E$9,MATCH("Produção",Módulos!$A$5:$A$9,0))="SIM",INDEX(Módulos!$E$5:$E$9,MATCH("Financeiro",Módulos!$A$5:$A$9,0))="SIM"),"SIM","NÃO") -> NÃO
A8: Financeiro | B8: Produção | C8: Custo por minuto produzido, margem por cliente | D8: 'Cliente X dá 70% de eficiência mas 12% de margem' | E8: =IF(AND(INDEX(Módulos!$E$5:$E$9,MATCH("Financeiro",Módulos!$A$5:$A$9,0))="SIM",INDEX(Módulos!$E$5:$E$9,MATCH("Produção",Módulos!$A$5:$A$9,0))="SIM"),"SIM","NÃO") -> NÃO
A9: Produção | B9: Secretária | C9: Prazo de OP vira compromisso de entrega; atraso vira retorno ao cliente | D9: 'Avisar o cliente da OP 4471 que atrasa 2 dias' | E9: =IF(AND(INDEX(Módulos!$E$5:$E$9,MATCH("Produção",Módulos!$A$5:$A$9,0))="SIM",INDEX(Módulos!$E$5:$E$9,MATCH("Secretária",Módulos!$A$5:$A$9,0))="SIM"),"SIM","NÃO") -> NÃO
A10: Documentos | B10: Financeiro | C10: Contrato gera recorrência; nota recebida vira lançamento | D10: contrato de aluguel → conta fixa todo dia 10 | E10: =IF(AND(INDEX(Módulos!$E$5:$E$9,MATCH("Documentos",Módulos!$A$5:$A$9,0))="SIM",INDEX(Módulos!$E$5:$E$9,MATCH("Financeiro",Módulos!$A$5:$A$9,0))="SIM"),"SIM","NÃO") -> NÃO
A11: Documentos | B11: Secretária | C11: Validade vira lembrete | D11: alvará vence em 30 dias | E11: =IF(AND(INDEX(Módulos!$E$5:$E$9,MATCH("Documentos",Módulos!$A$5:$A$9,0))="SIM",INDEX(Módulos!$E$5:$E$9,MATCH("Secretária",Módulos!$A$5:$A$9,0))="SIM"),"SIM","NÃO") -> NÃO
A12: Documentos | B12: Produção | C12: Cadastro de cliente/colaboradora alimenta o AgilFac | D12: nova costureira cadastrada → já aparece para lançamento | E12: =IF(AND(INDEX(Módulos!$E$5:$E$9,MATCH("Documentos",Módulos!$A$5:$A$9,0))="SIM",INDEX(Módulos!$E$5:$E$9,MATCH("Produção",Módulos!$A$5:$A$9,0))="SIM"),"SIM","NÃO") -> NÃO
A13: Financeiro | B13: Documentos | C13: Comprovante e nota arquivados na pasta certa | D13: foto do boleto pago → pasta Douglas/2026-10 | E13: =IF(AND(INDEX(Módulos!$E$5:$E$9,MATCH("Financeiro",Módulos!$A$5:$A$9,0))="SIM",INDEX(Módulos!$E$5:$E$9,MATCH("Documentos",Módulos!$A$5:$A$9,0))="SIM"),"SIM","NÃO") -> NÃO
A14: Todos | B14: Diretor | C14: Resumos, alertas e números do dia | D14: resumo das 7h e análise semanal cruzada | E14: =IF(AND(TRUE(),TRUE()),"SIM","NÃO") -> SIM
A15: Diretor | B15: Todos | C15: Metas, prioridades, decisões do dono, contexto | D15: 'mês de foco em caixa' muda o tom de todos | E15: =IF(AND(TRUE(),TRUE()),"SIM","NÃO") -> SIM
A17: Ligações ativas | B17: =COUNTIF(E5:E15,"SIM") -> 2
A19: Matriz liga/desliga (SIM = ligação ativa; — = sem ligação direta)
A20: De \ Para | B20: Diretor | C20: Secretária | D20: Produção | E20: Documentos | F20: Financeiro
A21: Diretor | B21: — | C21: =IF(INDEX(Módulos!$E$5:$E$9,MATCH("Secretária",Módulos!$A$5:$A$9,0))="SIM","SIM","off") -> SIM | D21: =IF(INDEX(Módulos!$E$5:$E$9,MATCH("Produção",Módulos!$A$5:$A$9,0))="SIM","SIM","off") -> off | E21: =IF(INDEX(Módulos!$E$5:$E$9,MATCH("Documentos",Módulos!$A$5:$A$9,0))="SIM","SIM","off") -> off | F21: =IF(INDEX(Módulos!$E$5:$E$9,MATCH("Financeiro",Módulos!$A$5:$A$9,0))="SIM","SIM","off") -> off
A22: Secretária | B22: =IF(INDEX(Módulos!$E$5:$E$9,MATCH("Secretária",Módulos!$A$5:$A$9,0))="SIM","SIM","off") -> SIM | C22: — | D22: — | E22: — | F22: =IF(AND(INDEX(Módulos!$E$5:$E$9,MATCH("Secretária",Módulos!$A$5:$A$9,0))="SIM",INDEX(Módulos!$E$5:$E$9,MATCH("Financeiro",Módulos!$A$5:$A$9,0))="SIM"),"SIM","off") -> off
A23: Produção | B23: =IF(INDEX(Módulos!$E$5:$E$9,MATCH("Produção",Módulos!$A$5:$A$9,0))="SIM","SIM","off") -> off | C23: =IF(AND(INDEX(Módulos!$E$5:$E$9,MATCH("Produção",Módulos!$A$5:$A$9,0))="SIM",INDEX(Módulos!$E$5:$E$9,MATCH("Secretária",Módulos!$A$5:$A$9,0))="SIM"),"SIM","off") -> off | D23: — | E23: — | F23: =IF(AND(INDEX(Módulos!$E$5:$E$9,MATCH("Produção",Módulos!$A$5:$A$9,0))="SIM",INDEX(Módulos!$E$5:$E$9,MATCH("Financeiro",Módulos!$A$5:$A$9,0))="SIM"),"SIM","off") -> off
A24: Documentos | B24: =IF(INDEX(Módulos!$E$5:$E$9,MATCH("Documentos",Módulos!$A$5:$A$9,0))="SIM","SIM","off") -> off | C24: =IF(AND(INDEX(Módulos!$E$5:$E$9,MATCH("Documentos",Módulos!$A$5:$A$9,0))="SIM",INDEX(Módulos!$E$5:$E$9,MATCH("Secretária",Módulos!$A$5:$A$9,0))="SIM"),"SIM","off") -> off | D24: =IF(AND(INDEX(Módulos!$E$5:$E$9,MATCH("Documentos",Módulos!$A$5:$A$9,0))="SIM",INDEX(Módulos!$E$5:$E$9,MATCH("Produção",Módulos!$A$5:$A$9,0))="SIM"),"SIM","off") -> off | E24: — | F24: =IF(AND(INDEX(Módulos!$E$5:$E$9,MATCH("Documentos",Módulos!$A$5:$A$9,0))="SIM",INDEX(Módulos!$E$5:$E$9,MATCH("Financeiro",Módulos!$A$5:$A$9,0))="SIM"),"SIM","off") -> off
A25: Financeiro | B25: =IF(INDEX(Módulos!$E$5:$E$9,MATCH("Financeiro",Módulos!$A$5:$A$9,0))="SIM","SIM","off") -> off | C25: =IF(AND(INDEX(Módulos!$E$5:$E$9,MATCH("Financeiro",Módulos!$A$5:$A$9,0))="SIM",INDEX(Módulos!$E$5:$E$9,MATCH("Secretária",Módulos!$A$5:$A$9,0))="SIM"),"SIM","off") -> off | D25: =IF(AND(INDEX(Módulos!$E$5:$E$9,MATCH("Financeiro",Módulos!$A$5:$A$9,0))="SIM",INDEX(Módulos!$E$5:$E$9,MATCH("Produção",Módulos!$A$5:$A$9,0))="SIM"),"SIM","off") -> off | E25: =IF(AND(INDEX(Módulos!$E$5:$E$9,MATCH("Financeiro",Módulos!$A$5:$A$9,0))="SIM",INDEX(Módulos!$E$5:$E$9,MATCH("Documentos",Módulos!$A$5:$A$9,0))="SIM"),"SIM","off") -> off | F25: —

Sheet Fases
A1: Fases do projeto
A3: Fase | B3: Objetivo | C3: Início | D3: Semanas | E3: Fim (fórmula) | F3: Status | G3: Critério de saída | H3: Próximo passo
A4: 0 · Validação | B4: 10 empresários pagam antes de escrever código novo | C4: 46308 | D4: 2 | E4: =C4+D4*7 -> 46322 | F4: Não iniciada | G4: 10 pagantes (ou 5 + 5 compromissos firmes) e lista dos 5 pedidos mais frequentes | H4: Página de oferta + lista de 30 nomes
A5: 1 · MVP Telegram | B5: 10 clientes usando todo dia sem operação manual (piloto no Telegram) | C5: 46322 | D5: 3 | E5: =C5+D5*7 -> 46343 | F5: Não iniciada | G5: 10 ativos, ≥20 msgs/semana cada, 8 pagam o 2º mês | H5: Criar bot no @BotFather + adaptador de canal
A6: 2 · WhatsApp, painel e conta compartilhada | B6: Migrar para WhatsApp Cloud API; produto vendável para empresa de 20–100 pessoas | C6: 46343 | D6: 4 | E6: =C6+D6*7 -> 46371 | F6: Não iniciada | G6: 30 pagantes, ≥10 contas com 2+ usuários, churn < 8% | H6: Ativar WhatsApp no app Meta + Postgres
A7: 4 · Lançamento comercial | B7: Venda contínua sem mídia paga | C7: 46343 | D7: 6 | E7: =C7+D7*7 -> 46385 | F7: Não iniciada | G7: 5 vendas/semana orgânicas por 4 semanas seguidas | H7: Decidir nome e marca
A8: 3 · Financeiro e integrações | B8: Cobrar, ler extrato, emitir nota, AgilFac | C8: 46371 | D8: 6 | E8: =C8+D8*7 -> 46413 | F8: Não iniciada | G8: 50 clientes, ≥20% usando cobrança/financeiro | H8: Reavaliar escopo com clientes

Sheet Tarefas
A1: Tarefas por fase
A3: Fase | B3: Tarefa | C3: Responsável | D3: Status | E3: Prazo | F3: Observações
A4: 0 | B4: Definir a oferta em uma página (o que faz na 1ª semana, R$ 97/mês, 10 vagas) | C4: Kauê | D4: Não iniciada
A5: 0 | B5: Listar 30 candidatos (mentorados, Masi, empresários orientados) | C5: Kauê | D5: Não iniciada
A6: 0 | B6: 15 conversas de 20 min com roteiro | C6: Kauê | D6: Não iniciada
A7: 0 | B7: Pré-venda: cobrar 1º mês por Pix com data de entrega | C7: Kauê | D7: Não iniciada
A8: 0 | B8: Concierge: operar o bot atual à mão para 2–3 clientes | C8: Kauê | D8: Não iniciada
A9: 1 | B9: Canal Telegram: Bot API (reaproveita bot de agenda), webhook texto/áudio/imagem, adaptador de canal isolado | C9: Kauê + Claude Code | D9: Não iniciada
A10: 1 | B10: Orquestrador: transcrição, intenção, roteamento por persona | C10: Kauê + Claude Code | D10: Não iniciada
A11: 1 | B11: Agenda: Google Agenda por cliente (OAuth) + link do Meet | C11: Kauê + Claude Code | D11: Não iniciada
A12: 1 | B12: Tarefas e delegação (lembrete ao dono; cobrança ao colaborador só na v2) | C12: Kauê + Claude Code | D12: Não iniciada
A13: 1 | B13: Resumo diário às 7h | C13: Kauê + Claude Code | D13: Não iniciada
A14: 1 | B14: Metas da semana (define segunda, cobra sexta) | C14: Kauê + Claude Code | D14: Não iniciada
A15: 1 | B15: Ata de reunião → tarefas | C15: Kauê + Claude Code | D15: Não iniciada
... A34: 3 | B34: Termos de uso e LGPD | C34: Jurídico | D34: Não iniciada
A36: Resumo
A37: Não iniciada | B37: =COUNTIF($D$4:$D$34,A37) -> 31
A38: Em andamento | B38: =COUNTIF($D$4:$D$34,A38) -> 0
A39: Concluída | B39: =COUNTIF($D$4:$D$34,A39) -> 0
A40: Pausada | B40: =COUNTIF($D$4:$D$34,A40) -> 0
A41: Total | B41: =COUNTA($B$4:$B$34) -> 31
A42: % concluído | B42: =IF(B41=0,0,B39/B41) -> 0

Sheet Necessidades
A1: Contas, acessos e recursos
A3: Serviço | B3: Para quê | C3: Fase | D3: Status atual | E3: Ação
A4: Bot Telegram (@BotFather) | B4: Canal do piloto | C4: 1 | D4: Bot de agenda existe | E4: Criar bot novo com nome/avatar do assessor
A5: Número WhatsApp dedicado | B5: Canal definitivo | C5: 2 | D5: Pendente | E5: Comprar chip ou número virtual
A6: Evolution API (self-hosted) | B6: Plano B se piloto rejeitar Telegram | C6: 1 | D6: Pendente | E6: Só se necessário
A7: Google Cloud (OAuth Calendar/Meet) | B7: Agenda por cliente | C7: 1 | D7: Existe para o bot atual | E7: Publicar app para múltiplos usuários
A8: Gemini API | B8: IA e transcrição | C8: 1 | D8: Existe | E8: —
A9: Meta for Developers (WhatsApp) | B9: API oficial | C9: 2 | D9: App existe (Forzz) | E9: Adicionar produto WhatsApp, verificar empresa
A10: Cloudflare R2 / Backblaze | B10: Arquivos | C10: 2 | D10: Pendente | E10: Criar conta
A11: Asaas | B11: Assinatura e cobrança | C11: 2–3 | D11: Pendente | E11: Conta PJ + API
A12: Pluggy | B12: Open Finance | C12: 3 | D12: Pendente | E12: Contratar plano
A13: Focus NFe | B13: NFS-e | C13: 3 | D13: Pendente | E13: Contratar plano
A14: Domínio e SSL | B14: App e landing | C14: 2 | D14: Traefik/Let's Encrypt configurado | E14: Definir subdomínio
... A16: Dev Node (opcional) | B16: Se não houver 15 h/semana de Kauê | C16: 1–2 | D16: Decidir | E16: Contrato de 3 meses

Sheet Custos
A1: Custos mensais estimados por estágio (R$)
A3: Item | B3: MVP (10 clientes) | C3: Fase 2 (30 clientes) | D3: Fase 3 (50 clientes) | E3: Observação
A4: Número WhatsApp | B4: 0 | C4: 30 | D4: 30 | E4: Telegram grátis no MVP; chip a partir da Fase 2
A5: Gemini API | B5: 100 | C5: 300 | D5: 500 | E5: ~50 msgs/dia por cliente
A6: Meta Cloud API (conversas) | B6: 0 | C6: 200 | D6: 400 | E6: só a partir da Fase 2; conversas iniciadas pelo usuário têm 24 h grátis
A7: Armazenamento (R2/Backblaze) | B7: 0 | C7: 20 | D7: 40
A8: VPS extra | B8: 0 | C8: 50 | D8: 150 | E8: o atual aguenta até ~30 clientes
A9: Pluggy (Open Finance) | B9: 0 | C9: 0 | D9: 150 | E9: ~R$ 3 por conta conectada
A10: Focus NFe | B10: 0 | C10: 0 | D10: 80
A11: Asaas | B11: 0 | C11: 0 | D11: 0 | E11: por transação, sem fixo
A12: Custo fixo total | B12: =SUM(B4:B11) -> 100 | C12: =SUM(C4:C11) -> 600 | D12: =SUM(D4:D11) -> 1350
A14: Clientes | B14: 10 | C14: 30 | D14: 50
A15: Ticket médio (R$/mês) | B15: 97 | C15: 150 | D15: 150
A16: Receita | B16: =B14*B15 -> 970 | C16: =C14*C15 -> 4500 | D16: =D14*D15 -> 7500
A17: Margem | B17: =B16-B12 -> 870 | C17: =C16-C12 -> 3900 | D17: =D16-D12 -> 6150
A18: Margem % | B18: =IF(B16=0,0,B17/B16) -> 0.89690722 | C18: =IF(C16=0,0,C17/C16) -> 0.86666667 | D18: =IF(D16=0,0,D17/D16) -> 0.82
A20: Valores estimados por Kauê/Claude em 10/10/2026; ajustar com cotações reais. Amarelo = editável.

Sheet Cronograma
A1: Cronograma por semana (Gantt)
A2: Semanas contadas a partir de 13/10/2026. Início/duração vêm da aba Fases.
A3: Data base | B3: 46308 | D3: =$B$3+0 -> 46308 | E3: =$B$3+7 -> 46315 | F3: =$B$3+14 -> 46322 | G3: =$B$3+21 -> 46329 | H3: =$B$3+28 -> 46336 | I3: =$B$3+35 -> 46343 | J3: =$B$3+42 -> 46350 | K3: =$B$3+49 -> 46357 | L3: =$B$3+56 -> 46364 | M3: =$B$3+63 -> 46371 | N3: =$B$3+70 -> 46378 | O3: =$B$3+77 -> 46385 | P3: =$B$3+84 -> 46392 | Q3: =$B$3+91 -> 46399 | R3: =$B$3+98 -> 46406 | S3: =$B$3+105 -> 46413 | T3: =$B$3+112 -> 46420 | U3: =$B$3+119 -> 46427
A4: Fase | B4: Início | C4: Fim | D4: S1 | E4: S2 | F4: S3 | G4: S4 | H4: S5 | I4: S6 | J4: S7 | K4: S8 | L4: S9 | M4: S10 | N4: S11 | O4: S12 | P4: S13 | Q4: S14 | R4: S15 | S4: S16 | T4: S17 | U4: S18
A5: =Fases!A4 -> 0 · Validação | B5: =Fases!C4 -> 46308 | C5: =Fases!E4 -> 46322 | D5: =IF(AND(D$3>=$B5,D$3<$C5),"■","") -> ■ | E5: =IF(AND(E$3>=$B5,E$3<$C5),"■","") -> ■ | F5: =IF(AND(F$3>=$B5,F$3<$C5),"■","") | G5: =IF(AND(G$3>=$B5,G$3<$C5),"■","") | H5: =IF(AND(H$3>=$B5,H$3<$C5),"■","") | I5: =IF(AND(I$3>=$B5,I$3<$C5),"■","") | J5: =IF(AND(J$3>=$B5,J$3<$C5),"■","") | K5: =IF(AND(K$3>=$B5,K$3<$C5),"■","") | ... U5: =IF(AND(U$3>=$B5,U$3<$C5),"■","")
A6: =Fases!A5 -> 1 · MVP Telegram | B6: =Fases!C5 -> 46322 | C6: =Fases!E5 -> 46343 | D6: =IF(AND(D$3>=$B6,D$3<$C6),"■","") | E6: =IF(AND(E$3>=$B6,E$3<$C6),"■","") | F6: =IF(AND(F$3>=$B6,F$3<$C6),"■","") -> ■ | G6: =IF(AND(G$3>=$B6,G$3<$C6),"■","") -> ■ | H6: =IF(AND(H$3>=$B6,H$3<$C6),"■","") -> ■ | I6: =IF(AND(I$3>=$B6,I$3<$C6),"■","") | J6: =IF(AND(J$3>=$B6,J$3<$C6),"■","") | K6: =IF(AND(K$3>=$B6,K$3<$C6),"■","") | ... U6: =IF(AND(U$3>=$B6,U$3<$C6),"■","")
A7: =Fases!A6 -> 2 · WhatsApp, painel e conta compartilhada | B7: =Fases!C6 -> 46343 | C7: =Fases!E6 -> 46371 | D7: =IF(AND(D$3>=$B7,D$3<$C7),"■","") | E7: =IF(AND(E$3>=$B7,E$3<$C7),"■","") | F7: =IF(AND(F$3>=$B7,F$3<$C7),"■","") | G7: =IF(AND(G$3>=$B7,G$3<$C7),"■","") | H7: =IF(AND(H$3>=$B7,H$3<$C7),"■","") | I7: =IF(AND(I$3>=$B7,I$3<$C7),"■","") -> ■ | J7: =IF(AND(J$3>=$B7,J$3<$C7),"■","") -> ■ | K7: =IF(AND(K$3>=$B7,K$3<$C7),"■","") -> ■ | ... U7: =IF(AND(U$3>=$B7,U$3<$C7),"■","")
A8: =Fases!A7 -> 4 · Lançamento comercial | B8: =Fases!C7 -> 46343 | C8: =Fases!E7 -> 46385 | D8: =IF(AND(D$3>=$B8,D$3<$C8),"■","") | E8: =IF(AND(E$3>=$B8,E$3<$C8),"■","") | F8: =IF(AND(F$3>=$B8,F$3<$C8),"■","") | G8: =IF(AND(G$3>=$B8,G$3<$C8),"■","") | H8: =IF(AND(H$3>=$B8,H$3<$C8),"■","") | I8: =IF(AND(I$3>=$B8,I$3<$C8),"■","") -> ■ | J8: =IF(AND(J$3>=$B8,J$3<$C8),"■","") -> ■ | K8: =IF(AND(K$3>=$B8,K$3<$C8),"■","") -> ■ | ... U8: =IF(AND(U$3>=$B8,U$3<$C8),"■","")
A9: =Fases!A8 -> 3 · Financeiro e integrações | B9: =Fases!C8 -> 46371 | C9: =Fases!E8 -> 46413 | D9: =IF(AND(D$3>=$B9,D$3<$C9),"■","") | E9: =IF(AND(E$3>=$B9,E$3<$C9),"■","") | F9: =IF(AND(F$3>=$B9,F$3<$C9),"■","") | G9: =IF(AND(G$3>=$B9,G$3<$C9),"■","") | H9: =IF(AND(H$3>=$B9,H$3<$C9),"■","") | I9: =IF(AND(I$3>=$B9,I$3<$C9),"■","") | J9: =IF(AND(J$3>=$B9,J$3<$C9),"■","") | K9: =IF(AND(K$3>=$B9,K$3<$C9),"■","") | ... U9: =IF(AND(U$3>=$B9,U$3<$C9),"■","")

Sheet Riscos
A1: Riscos
A3: Risco | B3: Impacto | C3: Probabilidade | D3: Mitigação | E3: Status
A4: Tempo de Kauê dividido entre 5 empresas | B4: Alto | C4: Alta | D4: Fase 0 antes de código; sem 15 h/semana, contratar dev por 3 meses | E4: Aberto
A5: Cliente recusa usar Telegram no piloto | B5: Alto | C5: Média | D5: Perguntar na Fase 0; se >50% recusar, Evolution API no WhatsApp; Cloud API na Fase 2 | E5: Aberto
A6: IA erra ação com efeito externo | B6: Alto | C6: Média | D6: Confirmação obrigatória antes de mensagem a terceiro; recibo de tudo | E6: Aberto
A7: Meu Assessor lança módulo empresa | B7: Médio | C7: Média | D7: Diferencial é método KM + distribuição + AgilFac | E7: Aberto
A8: Cliente quer financeiro no MVP | B8: Médio | C8: Alta | D8: Dizer não; apontar Meu Assessor para pessoal até o v3 | E8: Aberto
A9: Dados financeiros sem base jurídica | B9: Alto | C9: Baixa | D9: Termos e política antes da Fase 3; Open Finance só leitura | E9: Aberto
A10: Custo por conversa da Meta cresce | B10: Médio | C10: Média | D10: Limitar mensagens proativas a 1–2/dia | E10: Aberto

Sheet Decisões
A1: Decisões em aberto (só Kauê)
A3: Decisão | B3: Opções | C3: Decidido | D3: Data | E3: Justificativa
A4: Nome | B4: Marca própria / dentro da marca KM
A5: Preço de fundador | B5: R$ 97 / R$ 147
A6: Nicho inicial | B6: Mentorados / sócios de confecção (AgilFac)
A7: Horas por semana nas Fases 1–2 | B7: 10 / 15 / 20
A8: Dev | B8: Só Kauê + Claude Code / dev contratado 3 meses
A9: Base técnica | B9: Reaproveitar bot Python / reescrever em Node
A10: Canal do piloto | B10: Telegram (decidido 11/10) / Evolution API se piloto recusar | C10: Telegram | D10: 46306 | E10: Gratuito, sem bloqueio, reaproveita bot; migra na Fase 2
